README
setup.py
uwsgidecorators.py
uWSGI_pipenv.egg-info/PKG-INFO
uWSGI_pipenv.egg-info/SOURCES.txt
uWSGI_pipenv.egg-info/dependency_links.txt
uWSGI_pipenv.egg-info/top_level.txt