Metadata-Version: 1.1
Name: uWSGI-pipenv
Version: 2.0.18
Summary: The uWSGI server (patched to not cause problems with pipenv+windows)
Home-page: https://uwsgi-docs.readthedocs.io/en/latest/
Author: Unbit
Author-email: info@unbit.it
License: GPLv2+
Platform: UNKNOWN
Classifier: Development Status :: 5 - Production/Stable
Classifier: License :: OSI Approved :: GNU General Public License v2 or later (GPLv2+)
Classifier: Programming Language :: Python
Classifier: Programming Language :: Python :: 2
Classifier: Programming Language :: Python :: 2.6
Classifier: Programming Language :: Python :: 2.7
Classifier: Programming Language :: Python :: 3
Classifier: Programming Language :: Python :: 3.4
Classifier: Programming Language :: Python :: 3.5
Classifier: Programming Language :: Python :: 3.6
